{
    "fam_leads": {
        "2288664": {
            "first_name": "Erin",
            "last_name": "Le"
        },
        "2375186": {
            "first_name": "Jaedon",
            "last_name": "Matamoros"
        },
        "2052873": {
            "first_name": "Kevin",
            "last_name": "Trinh"
        }
    },
    "fam_members": {
        "2374990": {
            "first_name": "Hermez",
            "last_name": "Tejeda"
        }
    },
    "fam_psuedos": {
        "2368355": {
            "first_name": "Jonathan",
            "last_name": "Thai"
        },
        "2335658": {
            "first_name": "Brendan",
            "last_name": "Chen"
        },
        "2297424": {
            "first_name": "Faith",
            "last_name": "Lee"
        },
        "2256627": {
            "first_name": "Angelina",
            "last_name": "Tran"
        },
        "2309322": {
            "first_name": "Chase",
            "last_name": "Nguyen"
        }
    }
}